setup.py
django_beautifulsoup_test.egg-info/PKG-INFO
django_beautifulsoup_test.egg-info/SOURCES.txt
django_beautifulsoup_test.egg-info/dependency_links.txt
django_beautifulsoup_test.egg-info/requires.txt
django_beautifulsoup_test.egg-info/top_level.txt
django_bs_test/__init__.py