Metadata-Version: 1.0
Name: django-beautifulsoup-test
Version: 1.0.1
Summary: TestCase class for using BeautifulSoup with Django tests
Home-page: https://github.com/jscott1989/django-beautifulsoup-test
Author: Jonathan Scott
Author-email: jonathan@jscott.me
License: UNKNOWN
Platform: UNKNOWN
